holdem_sim/__init__.py
holdem_sim/main.py
holdem_sim/poker_functions.py
holdem_sim/simulation.py
holdem_sim-0.1.1.dist-info/LICENSE
holdem_sim-0.1.1.dist-info/METADATA
holdem_sim-0.1.1.dist-info/WHEEL
holdem_sim-0.1.1.dist-info/RECORD
