Metadata-Version: 2.1
Name: holdem-sim
Version: 0.1.1
Summary: Get probablilites, odds, and win expectations for holdem hands
License: MIT
Author: Jay Cohen
Requires-Python: >=3.9,<4.0
Classifier: License :: OSI Approved :: MIT License
Classifier: Programming Language :: Python :: 3
Classifier: Programming Language :: Python :: 3.9
Classifier: Programming Language :: Python :: 3.10
Classifier: Programming Language :: Python :: 3.11
Requires-Dist: prettytable (>=3.6.0,<4.0.0)
